qcorrect/__init__.py
qcorrect/py.typed
qcorrect-0.0.0.dist-info/METADATA
qcorrect-0.0.0.dist-info/WHEEL
qcorrect-0.0.0.dist-info/RECORD
