Metadata-Version: 2.4
Name: qcorrect
Version: 0.0.0
Summary: Quantinuum error correction tools
Author-email: Seyon Sivarajah <seyon.sivarajah@quantinuum.com>
Requires-Python: >=3.9
